LICENSE
MANIFEST.in
README.rst
setup.cfg
setup.py
ktalon.egg-info/PKG-INFO
ktalon.egg-info/SOURCES.txt
ktalon.egg-info/dependency_links.txt
ktalon.egg-info/requires.txt
ktalon.egg-info/top_level.txt
talon/__init__.py
talon/constants.py
talon/html_quotations.py
talon/quotations.py
talon/utils.py
tests/__init__.py
tests/html_quotations_test.py
tests/quotations_test.py
tests/text_quotations_test.py
tests/utils_test.py
tests/fixtures/__init__.py