Metadata-Version: 1.0
Name: ktalon
Version: 1.5.3
Summary: Email quoted message striping re-purposed from talon
Home-page: https://github.com/kayako/ktalon
Author: Mailgun Inc.
Author-email: admin@mailgunhq.com
License: UNKNOWN
Platform: UNKNOWN
